currency_converter/__init__.py
currency_converter/core.py
simple_currency_converter_rahit-0.1.0.dist-info/METADATA
simple_currency_converter_rahit-0.1.0.dist-info/WHEEL
simple_currency_converter_rahit-0.1.0.dist-info/top_level.txt
simple_currency_converter_rahit-0.1.0.dist-info/RECORD
