Metadata-Version: 2.4
Name: simple-currency-converter-rahit
Version: 0.1.0
Summary: A simple currency conversion library for USD, BDT, EUR, JPY, NPR, and UZS.
Author-email: Rahitasswa Chakma <chakmarahit707@gmail.com>
License: MIT
Project-URL: Homepage, https://github.com/chakmarahit707-cyber?tab=packages
Keywords: currency,converter,exchange rates
Classifier: Programming Language :: Python :: 3
Classifier: License :: OSI Approved :: MIT License
Classifier: Operating System :: OS Independent
Requires-Python: >=3.8
